more_properties/__init__.py
more_properties/cached_property.py
more_properties/class_property.py
more_properties/property.py
more_properties/types.py
more_properties/util_properties.py
more_properties-1.1.0.dist-info/LICENSE
more_properties-1.1.0.dist-info/METADATA
more_properties-1.1.0.dist-info/WHEEL
more_properties-1.1.0.dist-info/top_level.txt
more_properties-1.1.0.dist-info/RECORD
