Metadata-Version: 2.1
Name: more-properties
Version: 1.1.0
Summary: A collection of property variants
Home-page: https://github.com/madman-bob/python-more-properties
Author: Robert Wright
Author-email: madman.bob@hotmail.co.uk
License: MIT
Platform: UNKNOWN
Classifier: License :: OSI Approved :: MIT License
Classifier: Programming Language :: Python :: 3
Classifier: Programming Language :: Python :: 3.6
Classifier: Programming Language :: Python :: 3.7
Classifier: Programming Language :: Python :: 3.8
Requires-Python: >=3.6
Requires-Dist: dataclasses
Requires-Dist: twine
